FolderStructure/__init__.py
FolderStructure/create_folder_structure.py
FolderStructure/folder_structure.py
FolderStructure/generate_folder_structure.py
SimpleFolderStructure-0.1.2.dist-info/LICENSE
SimpleFolderStructure-0.1.2.dist-info/METADATA
SimpleFolderStructure-0.1.2.dist-info/WHEEL
SimpleFolderStructure-0.1.2.dist-info/entry_points.txt
SimpleFolderStructure-0.1.2.dist-info/top_level.txt
SimpleFolderStructure-0.1.2.dist-info/RECORD
