Metadata-Version: 2.1
Name: SimpleFolderStructure
Version: 0.1.2
Summary: Create folder structures from files
Home-page: https://gitlab.com/coreman14/folder-generation-python
Author: Coreman14
Author-email: 
License: Apache License 2.0
Platform: UNKNOWN
Classifier: Programming Language :: Python :: 3
Classifier: Programming Language :: Python :: 3 :: Only
Classifier: Programming Language :: Python :: 3.10
Classifier: Operating System :: OS Independent
Requires-Python: >=3.10
License-File: LICENSE
Requires-Dist: colorama (==0.4.4)
